MANIFEST.in
setup.cfg
setup.py
GUI/__init__.py
GUI/base.py
GUI/buttons.py
GUI/colors.py
GUI/draw.py
GUI/font.py
GUI/locals.py
GUI/math.py
GUI/text.py
GUI/vracabulous.py
GUI/geo/__init__.py
GUI/geo/basics.py
GUI/geo/bezier.py
GUI/gui_examples/__init__.py
GUI/gui_examples/bezier.py
GUI/gui_examples/buttons.py
GUI/gui_examples/empty_template.py
GUI/gui_examples/login.py
GUI/gui_examples/morpion.py
GUI/gui_examples/text.py
GUI/test/__init__.py
GUI/test/test_base.py
GUI/test/test_color.py
GUI/test/test_vracabulous.py
PygameGUILib.egg-info/PKG-INFO
PygameGUILib.egg-info/SOURCES.txt
PygameGUILib.egg-info/dependency_links.txt
PygameGUILib.egg-info/requires.txt
PygameGUILib.egg-info/top_level.txt