Metadata-Version: 1.1
Name: PygameGUILib
Version: 0.4a5
Summary: widgets for pygame wit ease
Home-page: https://github.com/ddorn/GUI
Author: Diego Dorn
Author-email: diego.dorn@free.fr
License: UNKNOWN
Keywords: pygame widget widgets gui
Platform: UNKNOWN
Classifier: Development Status :: 3 - Alpha
Classifier: Programming Language :: Python :: 3.5
Classifier: Programming Language :: Python :: 3.6
